{"id":"62xm9os1BIlbFTbDFstvsr","name":"c_replace_ltd_punct_w_space","description":"Replaces limited punctuation with space.","documentType":"CLEANSE","repoInfo":{"repoPath":"","repoHandle":"62xm9os1BIlbFTbDFstvsr"},"docRef":null,"customAttributes":{"stringAttrs":[{"name":"ReferencedPublishingAllowed","value":"true"}]},"nativeData":{"id":"62xm9os1BIlbFTbDFstvsr","documentBlob":"{\"id\":\"6\",\"name\":\"c_replace_ltd_punct_w_space\",\"description\":\"Replaces limited punctuation with space.\",\"inputs\":[{\"id\":1,\"precision\":255,\"scale\":0,\"type\":\"string\",\"name\":\"c_replace_ltd_punct_w_space\"}],\"outputs\":[{\"id\":2,\"precision\":255,\"scale\":0,\"type\":\"string\",\"name\":\"c_replace_ltd_punct_w_space\"}],\"fieldTestData\":[{\"cleanseFieldId\":1,\"testData\":[\"test test\",\"remove/ltd_punct\",\",.!check!before\",\"remove///////ltd_punct\"]}],\"instances\":[{\"id\":9,\"name\":\"CleanseInstance\",\"inputs\":[1],\"outputs\":[2],\"steps\":[{\"id\":27,\"name\":\"Replace Values\",\"strategyType\":\"StandardizeStrategy\",\"strategySubType\":\"CLEANSE_REPLACE_CONTENT\",\"description\":\"Custom Strings\",\"delimiterList\":[],\"operations\":[{\"operationType\":\"SDOpReplaceCustomStrings\",\"scope\":\"0\",\"replacement\":\"  \",\"customStringList\":[\"/\",\"\\\\\",\".\",\"!\",\"_\",\"    \",\"   \",\"  \",\" \"]}],\"removeMultipleSpaces\":false,\"trim\":false},{\"id\":6,\"name\":\"Remove Spaces\",\"strategyType\":\"StandardizeStrategy\",\"strategySubType\":\"CLEANSE_REMOVE_SPACES\",\"description\":\"Leading And Trailing,Multiple Spaces\",\"delimiterList\":[],\"removeMultipleSpaces\":true,\"trim\":true}]}]}"}}