{
  "objectInfo" : {
    "id" : "kwx9WLtPG0igxMqQc8dZC9",
    "name" : "can_prename_gender_infa",
    "type" : "DICTIONARY",
    "metadata" : {
      "modelVersion" : {
        "major" : 1,
        "minor" : 0
      },
      "repoInfo" : {
        "repoHandle" : "kwx9WLtPG0igxMqQc8dZC9"
      },
      "contextAttributes" : [ ],
      "additionalInfo" : {
        "description" : "This reference table contains Gender on the basis of prename for Canada ",
        "contentType" : "Binary",
        "documentState" : "VALID"
      }
    }
  },
  "dataFileExtension" : "json",
  "updateTime" : "2024-04-03T14:44:46.680Z",
  "objectRefs" : [ ]
}