{
  "objectInfo" : {
    "id" : "e8wE5qYvcU0dFR1rKZlAsq",
    "name" : "p_Parse_Assign_GeocodingStatus_Desc",
    "type" : "PARSE",
    "metadata" : {
      "modelVersion" : {
        "major" : 1,
        "minor" : 0
      },
      "repoInfo" : {
        "repoHandle" : "e8wE5qYvcU0dFR1rKZlAsq"
      },
      "contextAttributes" : [ ],
      "additionalInfo" : {
        "description" : "Parse geocoding status description.",
        "contentType" : "Binary",
        "documentState" : "VALID"
      }
    }
  },
  "dataFileExtension" : "json",
  "updateTime" : "2024-04-03T14:44:46.841Z",
  "objectRefs" : [ {
    "id" : "469Cv4q39kEi1QJZeOPqOM",
    "name" : "dq_av_geocodingstatus_infa",
    "type" : "DICTIONARY",
    "metadata" : {
      "modelVersion" : {
        "major" : 1,
        "minor" : 0
      },
      "repoInfo" : {
        "repoHandle" : "469Cv4q39kEi1QJZeOPqOM"
      },
      "contextAttributes" : [ ],
      "additionalInfo" : {
        "description" : "Address Validation status with geocoding.",
        "contentType" : "Binary",
        "documentState" : "VALID"
      }
    },
    "path" : "/Explore/Data Quality/CDQ Americas Cmartin"
  } ]
}