{
  "objectInfo" : {
    "id" : "i5km4MMsgs5iKby4ySySk1",
    "name" : "p_Parse_SSN",
    "type" : "PARSE",
    "metadata" : {
      "modelVersion" : {
        "major" : 1,
        "minor" : 0
      },
      "repoInfo" : {
        "repoHandle" : "i5km4MMsgs5iKby4ySySk1"
      },
      "contextAttributes" : [ ],
      "additionalInfo" : {
        "description" : "Parse an SSN from a string.",
        "contentType" : "Binary",
        "documentState" : "VALID"
      }
    }
  },
  "dataFileExtension" : "json",
  "updateTime" : "2024-04-03T14:44:47.059Z",
  "objectRefs" : [ ]
}