{"id":"2yAPnbz2rsQiuMvV6B2jAs","name":"c_nzl_areacode_region","description":"Return name of the area code from the area code dialing prefix ","documentType":"CLEANSE","repoInfo":{"repoPath":"","repoHandle":"2yAPnbz2rsQiuMvV6B2jAs"},"docRef":null,"customAttributes":{"stringAttrs":[{"name":"ReferencedPublishingAllowed","value":"true"},{"name":"DIMENSION","value":"NONE"}]},"nativeData":{"id":"2yAPnbz2rsQiuMvV6B2jAs","documentBlob":"{\"id\":\"237\",\"name\":\"c_nzl_areacode_region\",\"description\":\"Return name of the area code from the area code dialing prefix \",\"inputs\":[{\"id\":1,\"precision\":255,\"scale\":0,\"type\":\"string\",\"name\":\"Cleanse\"}],\"outputs\":[{\"id\":2,\"precision\":255,\"scale\":0,\"type\":\"string\",\"name\":\"Cleanse_Cleansed\"}],\"fieldTestData\":[{\"cleanseFieldId\":1,\"testData\":[\"2\",\"02\",\"024099\",\"21234\",\"02test\",\"03\",\"30\",\"080\"]},{\"cleanseFieldId\":113,\"testData\":[]}],\"instances\":[{\"id\":3,\"name\":\"Instance1\",\"inputs\":[1],\"outputs\":[2],\"steps\":[{\"id\":133,\"name\":\"CLEANSE_REPLACE_CONTENT\",\"strategyType\":\"StandardizeStrategy\",\"strategySubType\":\"CLEANSE_REPLACE_CONTENT\",\"description\":\"nzl_tel_area_codes_infa\",\"delimiterList\":[\"_\"],\"operations\":[{\"operationType\":\"SDOpReplaceRefMatchValidValue\",\"scope\":\"0\",\"caseSensitive\":false,\"dictionary\":{\"name\":\"nzl_tel_area_codes_infa\",\"frsId\":\"2CL4fafL3CgjSusl9QaPW1\"}}],\"removeMultipleSpaces\":false,\"trim\":false}]}]}"}}