{"id":"3COEPNkUC0Giir6VdeKGq7","name":"c_nzl_phone_line","description":"Drops the area codes from a New Zealand phone number.","documentType":"CLEANSE","repoInfo":{"repoPath":"","repoHandle":"3COEPNkUC0Giir6VdeKGq7"},"docRef":null,"customAttributes":{"stringAttrs":[{"name":"ReferencedPublishingAllowed","value":"true"},{"name":"DIMENSION","value":"NONE"}]},"nativeData":{"id":"3COEPNkUC0Giir6VdeKGq7","documentBlob":"{\"id\":\"16\",\"name\":\"c_nzl_phone_line\",\"description\":\"Drops the area codes from a New Zealand phone number.\",\"inputs\":[{\"id\":1,\"precision\":255,\"scale\":0,\"type\":\"string\",\"name\":\"Cleanse\"}],\"outputs\":[{\"id\":2,\"precision\":255,\"scale\":0,\"type\":\"string\",\"name\":\"Cleanse_Cleansed\"}],\"fieldTestData\":[{\"cleanseFieldId\":1,\"testData\":[\"97001234\",\"24099456\",\"080123456\"]}],\"instances\":[{\"id\":3,\"name\":\"Instance1\",\"inputs\":[1],\"outputs\":[2],\"steps\":[{\"id\":505,\"name\":\"CLEANSE_REPLACE_CONTENT\",\"strategyType\":\"StandardizeStrategy\",\"strategySubType\":\"CLEANSE_REPLACE_CONTENT\",\"description\":\"CLEANSE_CUSTOM_STRINGS\",\"delimiterList\":[],\"operations\":[{\"operationType\":\"SDOpReplaceCustomStrings\",\"scope\":\"1\",\"replacement\":\"X\",\"customStringList\":[\"02499\",\"0240\",\"0800\",\"0900\",\"0508\",\"240\",\"508\",\"800\",\"900\",\"02\",\"03\",\"04\",\"06\",\"07\",\"09\",\"2\",\"3\",\"4\",\"6\",\"7\",\"9\",\"090\",\"080\",\"070\",\"050\"]}],\"removeMultipleSpaces\":false,\"trim\":false}]}]}"}}