{"id":"03bvJwrNT4Mlsv2oYw3pYC","name":"lbl_repeating_numbers","description":"The labeler uses a set list of repeating patterns that are labelled for the Spain CIF.","documentType":"LABELER","repoInfo":{"repoPath":"","repoHandle":"03bvJwrNT4Mlsv2oYw3pYC"},"docRef":null,"customAttributes":{"stringAttrs":[{"name":"ReferencedPublishingAllowed","value":"true"},{"name":"DIMENSION","value":"NONE"}]},"nativeData":{"id":"03bvJwrNT4Mlsv2oYw3pYC","documentBlob":"{\"id\":\"15\",\"name\":\"lbl_repeating_numbers\",\"description\":\"The labeler uses a set list of repeating patterns that are labelled for the Spain CIF.\",\"inputs\":[{\"id\":1,\"precision\":255,\"scale\":0,\"type\":\"string\",\"name\":\"lbl_repeating_numbers\"}],\"outputs\":[{\"id\":2,\"precision\":255,\"scale\":0,\"type\":\"string\",\"name\":\"LabeledOutput\"},{\"id\":3,\"precision\":255,\"scale\":0,\"type\":\"string\",\"name\":\"TokenizedData\"}],\"fieldTestData\":[{\"labelerFieldId\":1,\"testData\":[\"5555555\",\"0000000\",\"8080808080\"]}],\"customDelimiters\":[{\"id\":\"delim_row_488\",\"character\":\"<:>\",\"name\":\"Other\",\"type\":\"CUSTOM_OUTPUT\"}],\"instances\":[{\"id\":53,\"name\":\"LabelerInstance\",\"tokenMode\":true,\"inputs\":[1],\"outputs\":[2,3],\"steps\":[{\"id\":710,\"name\":\"CUSTOM_LABEL\",\"operation\":\"RegExOperation\",\"label\":\"Suspect\",\"description\":\"CUSTOM\",\"regex\":{\"value\":\"(.*)((01){3,}|(10){3,}|1{7,}|(12){3,}|(21){3,}|2{7,}|(23){3,}|(32){3,}|3{7,}|(34){3,}|(43){3,}|4{7,}|(45){3,}|(54){3,}|5{7,}|(56){3,}|(65){3,}|6{7,}|(67){3,}|(76){3,}|7{7,}|(78){3,}|(87){3,}|8{7,}|(89){3,}|(98){3,}|9{7,}|0{7,}|(20){3,}|(30){3,}|(40){3,}|(50){3,}|(60){3,}|(70){3,}|(80){3,}|(90){3,})(.*)\"}}],\"inputDelimiterList\":[\" \"],\"outputDelimiter\":\"<:>\",\"reverseEnabled\":false}]}"}}