{"id":"9VKHnbzIp1iiLvvC6KrPSL","name":"lbl_GBR_Area_Code_3Digits","description":"Labels 3 digit area codes of Great Britain.","documentType":"LABELER","repoInfo":{"repoPath":"","repoHandle":"9VKHnbzIp1iiLvvC6KrPSL"},"docRef":null,"customAttributes":{"stringAttrs":[{"name":"ReferencedPublishingAllowed","value":"true"}]},"nativeData":{"id":"9VKHnbzIp1iiLvvC6KrPSL","documentBlob":"{\"id\":\"105\",\"name\":\"lbl_GBR_Area_Code_3Digits\",\"description\":\"Labels 3 digit area codes of Great Britain.\",\"inputs\":[{\"id\":1,\"precision\":255,\"scale\":0,\"type\":\"string\",\"name\":\"lbl_GBR_Area_Code_3Digits\"}],\"outputs\":[{\"id\":2,\"precision\":255,\"scale\":0,\"type\":\"string\",\"name\":\"LabeledOutput\"},{\"id\":3,\"precision\":255,\"scale\":0,\"type\":\"string\",\"name\":\"TokenizedData\"}],\"fieldTestData\":[{\"labelerFieldId\":1,\"testData\":[]}],\"instances\":[{\"id\":143,\"name\":\"LabelerInstance\",\"tokenMode\":true,\"inputs\":[1],\"outputs\":[2,3],\"steps\":[{\"id\":226,\"name\":\"gbr_tel_area_codes_infa\",\"operation\":\"DictionaryOperation\",\"label\":\"3_digit_area_code\",\"dictionary\":{\"name\":\"gbr_tel_area_codes_infa\",\"validColumn\":\"Column 1\",\"frsId\":\"3B2p74Gjr4xdLSebE6NPC6\",\"caseSensitive\":false,\"standardization\":false,\"inclusiveMode\":true}},{\"id\":233,\"name\":\"gbr_tel_area_codes_infa\",\"operation\":\"DictionaryOperation\",\"label\":\"no_match\",\"dictionary\":{\"name\":\"gbr_tel_area_codes_infa\",\"validColumn\":\"Column 1\",\"frsId\":\"3B2p74Gjr4xdLSebE6NPC6\",\"caseSensitive\":false,\"standardization\":false,\"inclusiveMode\":false}}],\"inputDelimiterList\":[\" \"],\"outputDelimiter\":\" \",\"reverseEnabled\":false}]}"}}